jwbmisc/__init__.py
jwbmisc/_version.py
jwbmisc/collection.py
jwbmisc/exec.py
jwbmisc/fs.py
jwbmisc/interactive.py
jwbmisc/json.py
jwbmisc/keeper.py
jwbmisc/passwd.py
jwbmisc/string.py
jwbmisc-0.0.6.dist-info/licenses/LICENSE
jwbmisc-0.0.6.dist-info/METADATA
jwbmisc-0.0.6.dist-info/WHEEL
jwbmisc-0.0.6.dist-info/top_level.txt
jwbmisc-0.0.6.dist-info/RECORD
