Metadata-Version: 2.4
Name: jwbmisc
Version: 0.0.6
Summary: Misc util functions of jwb
Author-email: Joachim Bargsten <jw@bargsten.org>
License:                                  Apache License
Project-URL: homepage, https://github.com/jwbargsten/jwbmisc
Project-URL: repository, https://github.com/jwbargsten/jwbmisc
Requires-Python: >=3.11
License-File: LICENSE
Requires-Dist: pyyaml
Requires-Dist: more-itertools
Provides-Extra: dev
Requires-Dist: ruff; extra == "dev"
Requires-Dist: pytest>=7; extra == "dev"
Requires-Dist: setuptools_scm; extra == "dev"
Requires-Dist: mypy; extra == "dev"
Requires-Dist: pytest-env; extra == "dev"
Requires-Dist: pytest-mock; extra == "dev"
Requires-Dist: keepercommander; extra == "dev"
Requires-Dist: keyring; extra == "dev"
Provides-Extra: build
Requires-Dist: build; extra == "build"
Requires-Dist: twine; extra == "build"
Requires-Dist: tomli; extra == "build"
Requires-Dist: setuptools_scm; extra == "build"
Requires-Dist: check-manifest; extra == "build"
Requires-Dist: check-wheel-contents; extra == "build"
Requires-Dist: pyroma; extra == "build"
Provides-Extra: docs
Requires-Dist: sphinx; extra == "docs"
Requires-Dist: myst-parser; extra == "docs"
Requires-Dist: sphinx-sitemap; extra == "docs"
Requires-Dist: setuptools_scm; extra == "docs"
Requires-Dist: pydata-sphinx-theme; extra == "docs"
Requires-Dist: sphinx-autodoc-typehints; extra == "docs"
Requires-Dist: myst-nb; extra == "docs"
Provides-Extra: all
Requires-Dist: jwbmisc[build,dev,docs]; extra == "all"
Dynamic: license-file
